qhaven/__init__.py
qhaven/cli.py
qhaven/fixgen.py
qhaven/github.py
qhaven/report.py
qhaven/report_cbom.py
qhaven/report_html.py
qhaven/rules.py
qhaven/scanner.py
qhaven/assets/__init__.py
qhaven/assets/cnsa2.json
qhaven-0.7.3.dist-info/METADATA
qhaven-0.7.3.dist-info/WHEEL
qhaven-0.7.3.dist-info/entry_points.txt
qhaven-0.7.3.dist-info/top_level.txt
qhaven-0.7.3.dist-info/RECORD
