Metadata-Version: 2.4
Name: qhaven
Version: 0.7.3
Summary: PQC CBOM/PDF/HTML generator for CyberScope
Author-email: honkidori <qrypthaven@outlook.com>
License: MIT
Requires-Python: >=3.9
Requires-Dist: tqdm
Requires-Dist: reportlab
Requires-Dist: jinja2
Requires-Dist: tomli; python_version < "3.11"
Requires-Dist: requests
Requires-Dist: pyyaml
